printguard_shared/__init__.py
printguard_shared/constants.py
printguard_shared/crypto.py
printguard_shared-0.1.0.dist-info/METADATA
printguard_shared-0.1.0.dist-info/WHEEL
printguard_shared-0.1.0.dist-info/top_level.txt
printguard_shared-0.1.0.dist-info/RECORD
