Metadata-Version: 2.4
Name: printguard-shared
Version: 0.1.0
Summary: Shared utilities for PrintGuard backend and Home Assistant integration
Author-email: Oliver Bravery <dev@oliverbravery.uk>
Maintainer-email: Oliver Bravery <dev@oliverbravery.uk>
License: GPL-2.0-only
Project-URL: Homepage, https://github.com/oliverbravery/PrintGuard
Project-URL: Repository, https://github.com/oliverbravery/PrintGuard
Project-URL: Documentation, https://oliverbravery.github.io/PrintGuard/
Project-URL: Issues, https://github.com/oliverbravery/PrintGuard/issues
Project-URL: PyPI Package, https://pypi.org/project/printguard-shared/
Keywords: printguard,3d-printing,home-assistant,cryptography
Classifier: Intended Audience :: Developers
Classifier: License :: OSI Approved :: GNU General Public License v2 (GPLv2)
Classifier: Programming Language :: Python :: 3.13
Classifier: Topic :: Software Development :: Libraries :: Python Modules
Classifier: Topic :: Home Automation
Requires-Python: >=3.13
Requires-Dist: cryptography>=41.0.0
Provides-Extra: dev
Requires-Dist: pytest; extra == "dev"
Requires-Dist: build; extra == "dev"
Requires-Dist: twine; extra == "dev"
